{
  "global": {},
  "events": {
    "follower": {
      "enabled": true,
      "layout": "image-left",
      "imageUrl": "",
      "message": "{name} folgt dir jetzt!",
      "duration": 2,
      "textDelay": 0,
      "soundUrl": "",
      "soundVolume": 80,
      "bgColor": "rgba(0,0,0,0.00)",
      "animIn": "bounceInRight",
      "animOut": "bounceOutRight",
      "fontFamily": "Archivo",
      "fontSize": 12,
      "fontWeight": 700,
      "textColor": "#ffffff",
      "highlightColor": "#14d3aa",
      "platform": "twitch"
    },
    "sub": {
      "enabled": true,
      "layout": "image-left",
      "imageUrl": "",
      "message": "{name} hat abonniert!",
      "duration": 2,
      "textDelay": 0,
      "soundUrl": "",
      "soundVolume": 80,
      "bgColor": "rgba(0,0,0,0.00)",
      "animIn": "bounceInRight",
      "animOut": "bounceOutRight",
      "fontFamily": "Archivo",
      "fontSize": 12,
      "fontWeight": 700,
      "textColor": "#ffffff",
      "highlightColor": "#14d3aa",
      "platform": "twitch"
    },
    "resub": {
      "enabled": true,
      "layout": "image-left",
      "imageUrl": "",
      "message": "{name} hat {text}",
      "duration": 2,
      "textDelay": 0,
      "soundUrl": "",
      "soundVolume": 80,
      "bgColor": "rgba(0,0,0,0.00)",
      "animIn": "bounceInRight",
      "animOut": "bounceOutRight",
      "fontFamily": "Archivo",
      "fontSize": 12,
      "fontWeight": 700,
      "textColor": "#ffffff",
      "highlightColor": "#14d3aa",
      "platform": "twitch"
    },
    "subgift": {
      "enabled": true,
      "layout": "image-left",
      "imageUrl": "",
      "message": "{name} hat einen Sub verschenkt!",
      "duration": 2,
      "textDelay": 0,
      "soundUrl": "",
      "soundVolume": 80,
      "bgColor": "rgba(0,0,0,0.00)",
      "animIn": "bounceInRight",
      "animOut": "bounceOutRight",
      "fontFamily": "Archivo",
      "fontSize": 12,
      "fontWeight": 700,
      "textColor": "#ffffff",
      "highlightColor": "#14d3aa",
      "platform": "twitch"
    },
    "raid": {
      "enabled": true,
      "layout": "image-left",
      "imageUrl": "",
      "message": "{name} raided mit {viewers} Zuschauern!",
      "duration": 2,
      "textDelay": 0,
      "soundUrl": "",
      "soundVolume": 80,
      "bgColor": "rgba(0,0,0,0.00)",
      "animIn": "bounceInRight",
      "animOut": "bounceOutRight",
      "fontFamily": "Archivo",
      "fontSize": 12,
      "fontWeight": 700,
      "textColor": "#ffffff",
      "highlightColor": "#14d3aa",
      "platform": "twitch"
    },
    "bits": {
      "enabled": true,
      "layout": "image-left",
      "imageUrl": "",
      "message": "{name} hat {amount} Bits gecheert!",
      "duration": 2,
      "textDelay": 0,
      "soundUrl": "",
      "soundVolume": 80,
      "bgColor": "rgba(0,0,0,0.00)",
      "animIn": "bounceInRight",
      "animOut": "bounceOutRight",
      "fontFamily": "Archivo",
      "fontSize": 12,
      "fontWeight": 700,
      "textColor": "#ffffff",
      "highlightColor": "#14d3aa",
      "platform": "twitch"
    },
    "superchat": {
      "enabled": true,
      "layout": "image-left",
      "imageUrl": "",
      "message": "{name}: {text}",
      "duration": 2,
      "textDelay": 0,
      "soundUrl": "",
      "soundVolume": 80,
      "bgColor": "",
      "animIn": "bounceInRight",
      "animOut": "bounceOutRight",
      "fontFamily": "Archivo",
      "fontSize": 12,
      "fontWeight": 700,
      "textColor": "",
      "highlightColor": "",
      "platform": "youtube"
    },
    "supersticker": {
      "enabled": true,
      "layout": "image-left",
      "imageUrl": "",
      "message": "{name} hat einen Sticker gesendet!",
      "duration": 2,
      "textDelay": 0,
      "soundUrl": "",
      "soundVolume": 80,
      "bgColor": "",
      "animIn": "bounceInRight",
      "animOut": "bounceOutRight",
      "fontFamily": "Archivo",
      "fontSize": 12,
      "fontWeight": 700,
      "textColor": "",
      "highlightColor": "",
      "platform": "youtube"
    },
    "membership": {
      "enabled": true,
      "layout": "image-left",
      "imageUrl": "",
      "message": "{name} ist jetzt Mitglied!",
      "duration": 2,
      "textDelay": 0,
      "soundUrl": "",
      "soundVolume": 80,
      "bgColor": "",
      "animIn": "bounceInRight",
      "animOut": "bounceOutRight",
      "fontFamily": "Archivo",
      "fontSize": 12,
      "fontWeight": 700,
      "textColor": "",
      "highlightColor": "",
      "platform": "youtube"
    },
    "donation": {
      "enabled": true,
      "layout": "image-left",
      "imageUrl": "",
      "message": "{name} hat {amount} gespendet!",
      "duration": 2,
      "textDelay": 0,
      "soundUrl": "",
      "soundVolume": 80,
      "bgColor": "",
      "animIn": "bounceInRight",
      "animOut": "bounceOutRight",
      "fontFamily": "Archivo",
      "fontSize": 12,
      "fontWeight": 700,
      "textColor": "",
      "highlightColor": "",
      "platform": "general"
    },
    "test": {
      "enabled": true,
      "layout": "image-left",
      "imageUrl": "",
      "message": "{text}",
      "duration": 2,
      "textDelay": 0,
      "soundUrl": "",
      "soundVolume": 80,
      "bgColor": "",
      "animIn": "bounceInRight",
      "animOut": "bounceOutRight",
      "fontFamily": "Archivo",
      "fontSize": 12,
      "fontWeight": 700,
      "textColor": "",
      "highlightColor": "",
      "platform": "test"
    }
  },
  "customEvents": [],
  "testSamples": {
    "follower": {
      "author": "ExampleUser",
      "text": "just followed",
      "amount": "",
      "viewers": ""
    },
    "sub": {
      "author": "ExampleUser",
      "text": "subscribed for 1 month",
      "amount": "",
      "viewers": ""
    }
  }
}